moria/__init__.py
moria/arch.py
moria/basetypes.py
moria/namespace.py
moria/pack.py
moria/util.py
moria/values.py
moria/parsers/__init__.py
moria/parsers/dwarf.py
moria_c-0.3.1.dist-info/METADATA
moria_c-0.3.1.dist-info/WHEEL
moria_c-0.3.1.dist-info/top_level.txt
moria_c-0.3.1.dist-info/RECORD
