Metadata-Version: 2.1
Name: moria-c
Version: 0.3.1
Summary: A library for manipulating in-memory C data structures
Home-page: https://github.com/josconno/moria
Author: Joe Connor
Author-email: josconno@gmail.com
License: UNKNOWN
Platform: UNKNOWN
Classifier: Programming Language :: Python :: 3.7
Classifier: Programming Language :: Python :: 3.8
Classifier: Programming Language :: Python :: 3.9
Requires-Python: >=3.7
Requires-Dist: pyelftools (>=0.27)
